CHANGES.rst
CONTRIBUTORS.rst
MANIFEST.in
README.rst
VERSION
VERSION_SUFFIX
setup.py
docs/LICENSE.GPL
docs/LICENSE.rst
docs/index.rst
src/visaplan/__init__.py
src/visaplan.plone.interfaces.egg-info/PKG-INFO
src/visaplan.plone.interfaces.egg-info/SOURCES.txt
src/visaplan.plone.interfaces.egg-info/dependency_links.txt
src/visaplan.plone.interfaces.egg-info/entry_points.txt
src/visaplan.plone.interfaces.egg-info/namespace_packages.txt
src/visaplan.plone.interfaces.egg-info/not-zip-safe
src/visaplan.plone.interfaces.egg-info/requires.txt
src/visaplan.plone.interfaces.egg-info/top_level.txt
src/visaplan/plone/__init__.py
src/visaplan/plone/interfaces/__init__.py
src/visaplan/plone/interfaces/behaviors.py
src/visaplan/plone/interfaces/behaviors.zcml
src/visaplan/plone/interfaces/configure.zcml
src/visaplan/plone/interfaces/factories.py
src/visaplan/plone/interfaces/tests/test_doctests.py