Metadata-Version: 1.1
Name: visaplan.plone.interfaces
Version: 1.0.dev2
Summary: Interfaces for a family of Plone/Dexterity datatypes
Home-page: https://pypi.org/project/visaplan.plone.interfaces
Author: Tobias Herp
Author-email: tobias.herp@visaplan.com
License: GPL version 2
Platform: UNKNOWN
Classifier: Environment :: Web Environment
Classifier: Framework :: Plone
Classifier: Framework :: Plone :: 4.3
Classifier: Programming Language :: Python
Classifier: Programming Language :: Python :: 2.7
Classifier: Intended Audience :: Developers
Classifier: Natural Language :: German
Classifier: Operating System :: OS Independent
Classifier: License :: OSI Approved :: GNU General Public License v2 (GPLv2)
